CHANGES.rst
LICENSE
ez_setup.py
setup.cfg
setup.py
pyramid_restlogging/__init__.py
pyramid_restlogging/views.py
pyramid_restlogging.egg-info/PKG-INFO
pyramid_restlogging.egg-info/SOURCES.txt
pyramid_restlogging.egg-info/dependency_links.txt
pyramid_restlogging.egg-info/entry_points.txt
pyramid_restlogging.egg-info/requires.txt
pyramid_restlogging.egg-info/top_level.txt
pyramid_restlogging/tests/__init__.py
pyramid_restlogging/tests/test_functional.py
pyramid_restlogging/tests/test_unit.py