Metadata-Version: 1.0
Name: pyramid-restlogging
Version: 0.2.38
Summary: Log rest resource
Home-page: UNKNOWN
Author: UNKNOWN
Author-email: UNKNOWN
License: UNKNOWN
Platform: UNKNOWN
